sprun/__init__.py
sprun/spr.py
tests/__init__.py
tests/manual_check.py
tests/test_runner.py
sprun-0.0.3.dist-info/LICENSE
sprun-0.0.3.dist-info/METADATA
sprun-0.0.3.dist-info/WHEEL
sprun-0.0.3.dist-info/top_level.txt
sprun-0.0.3.dist-info/RECORD
