Metadata-Version: 2.1
Name: sprun
Version: 0.0.3
Summary: subprocess run, simply execute a list of commands
Home-page: https://gitlab.com/a4z/sprun
Author: Harald Achitz
Author-email: harald.achitz@gmail.com
License: UNKNOWN
Project-URL: Bug Tracker, https://gitlab.com/a4z/sprun/issues
Platform: UNKNOWN
Classifier: Programming Language :: Python :: 3
Classifier: License :: OSI Approved :: MIT License
Classifier: Operating System :: OS Independent
Requires-Python: >=3.6
